yamsl/__init__.py
yamsl/meteoswiss.py
yamsl-0.1.0.dist-info/METADATA
yamsl-0.1.0.dist-info/WHEEL
yamsl-0.1.0.dist-info/top_level.txt
yamsl-0.1.0.dist-info/RECORD
