Metadata-Version: 2.1
Name: yamsl
Version: 0.1.0
Summary: Yet Another Meteo Swiss Library
Home-page: https://github.com/gwrd-ch/yamsl
Author: gwrd-ch
Author-email: dev@gwrd.ch
License: MIT
Platform: UNKNOWN
Classifier: Intended Audience :: Developers
Classifier: License :: OSI Approved :: MIT License
Classifier: Programming Language :: Python
Classifier: Programming Language :: Python :: 3
Classifier: Programming Language :: Python :: 3.6
Classifier: Programming Language :: Python :: 3.7
Classifier: Programming Language :: Python :: 3.8
Classifier: Programming Language :: Python :: 3.9
Classifier: Operating System :: OS Independent
Requires-Dist: aiohttp
